logBlizzard/__init__.py
logBlizzard/api_web_server.py
logBlizzard/clustersearch.py
logBlizzard/crypto.py
logBlizzard/localcfg.json
logBlizzard/localsearch.py
logBlizzard/logBlizzard.py
logBlizzard/network_cfg.json
logBlizzard/nodemanager.py
logBlizzard/pwf
logBlizzard/salt
logBlizzard/search_api.py
logBlizzard/syslog.py
logBlizzard-0.5.dev9.data/data/localcfg.json
logBlizzard-0.5.dev9.data/data/network_cfg.json
logBlizzard-0.5.dev9.data/data/pwf
logBlizzard-0.5.dev9.data/data/salt
logBlizzard-0.5.dev9.dist-info/DESCRIPTION.rst
logBlizzard-0.5.dev9.dist-info/METADATA
logBlizzard-0.5.dev9.dist-info/RECORD
logBlizzard-0.5.dev9.dist-info/WHEEL
logBlizzard-0.5.dev9.dist-info/metadata.json
logBlizzard-0.5.dev9.dist-info/top_level.txt
