Metadata-Version: 2.0
Name: logBlizzard
Version: 0.5.dev9
Summary: a distributed logging framework
Home-page: https://github.com/kriswans/logBlizzard
Author: Kris Swanson
Author-email: kriswans@cisco.com
License: MIT
Keywords: logging,syslog,IP-Multicast
Platform: UNKNOWN
Classifier: Development Status :: 3 - Alpha
Classifier: Intended Audience :: Developers
Classifier: Topic :: Software Development :: Build Tools
Classifier: License :: OSI Approved :: MIT License
Classifier: Programming Language :: Python :: 3.6
Requires-Python: >=3.5
Requires-Dist: cryptography
Requires-Dist: flask
